enums.py
enums-0.0.2.dist-info/DESCRIPTION.rst
enums-0.0.2.dist-info/METADATA
enums-0.0.2.dist-info/metadata.json
enums-0.0.2.dist-info/RECORD
enums-0.0.2.dist-info/top_level.txt
enums-0.0.2.dist-info/WHEEL
